Metadata-Version: 2.1
Name: sirdratutipackage
Version: 0.1
Summary: i love python
Home-page: UNKNOWN
License: UNKNOWN
Platform: UNKNOWN
